Metadata-Version: 1.0
Name: dist-probab
Version: 0.1
Summary: Gaussian and Binomial distributions
Home-page: UNKNOWN
Author: Tuba Siddiqui
Author-email: tubazamansiddiqui@gmail.com
License: UNKNOWN
Platform: UNKNOWN
